mediqbox/download/__init__.py
mediqbox/download/download.py
mediqbox_download-0.0.3.dist-info/LICENSE
mediqbox_download-0.0.3.dist-info/METADATA
mediqbox_download-0.0.3.dist-info/WHEEL
mediqbox_download-0.0.3.dist-info/top_level.txt
mediqbox_download-0.0.3.dist-info/RECORD
