Metadata-Version: 2.1
Name: mediqbox-download
Version: 0.0.3
Summary: A mediqbox component for downloading files
License-File: LICENSE
Requires-Dist: mediqbox-abc ==0.0.4
Requires-Dist: aiofiles
Requires-Dist: aiohttp
